_config/__init__.py
_datetime/__init__.py
db/__init__.py
nfetl/__init__.py
nfetl/_datetime/__init__.py
nfetl/core/__init__.py
nfetl/db/__init__.py
nfetl/processes/__init__.py
nfetl/processes/extract/__init__.py
nfetl/processes/load/__init__.py
nfetl/processes/transform/__init__.py
nfetl/tests/__init__.py
nfetl/tests/_datetime/__init__.py
nfetl/tests/_datetime/test__date.py
nfetl/tests/core/__init__.py
nfetl/tests/core/test_core.py
nfetl/tests/db/__init__.py
nfetl/tests/db/test_db.py
nfetl/tests/processes/__init__.py
nfetl/tests/processes/test_extract.py
nfetl/tests/processes/test_load.py
nfetl/tests/processes/test_transform.py
processes/__init__.py
processes/extract/__init__.py
processes/load/__init__.py
processes/transform/__init__.py
tests/__init__.py
tests/_config/__init__.py
tests/_config/test__config.py
tests/_datetime/__init__.py
tests/_datetime/test_date.py
tests/db/__init__.py
tests/processes/__init__.py
tests/processes/test_extract.py
tests/processes/test_load.py
tests/processes/test_transform.py
nfetl-0.9.0.dist-info/LICENSE.txt
nfetl-0.9.0.dist-info/METADATA
nfetl-0.9.0.dist-info/WHEEL
nfetl-0.9.0.dist-info/top_level.txt
nfetl-0.9.0.dist-info/RECORD
