Metadata-Version: 2.1
Name: nfetl
Version: 0.9.0
Summary: A package for creating a database containing NFL stats.
Home-page: UNKNOWN
Author: Dan Eschman
Author-email: dan.eschman@gmail.com
License: GNU AGPLv3
Platform: UNKNOWN
Classifier: Development Status :: 4 - Beta
Classifier: Intended Audience :: Developers
Classifier: Intended Audience :: Science/Research
Classifier: License :: OSI Approved :: GNU Affero General Public License v3
Classifier: Natural Language :: English
Classifier: Operating System :: Microsoft :: Windows
Classifier: Programming Language :: Python :: 3
Classifier: Topic :: Database
Classifier: Topic :: Games/Entertainment
Classifier: Topic :: Internet
Classifier: Topic :: Text Processing
Requires-Python: >=3.7
Requires-Dist: pytest
Requires-Dist: bs4
Requires-Dist: pandas
Requires-Dist: dask
